example/__init__.py
example/cartpole/__init__.py
example/cartpole/cartpole_acet_learning.py
example/cartpole/helper/__init__.py
example/cartpole/helper/cartpole_discretiser.py
example/cartpole/helper/env_wrapper.py
spyrl/__init__.py
spyrl/activity/__init__.py
spyrl/activity/activity.py
spyrl/activity/activity_config.py
spyrl/activity/activity_context.py
spyrl/activity/learning.py
spyrl/activity/testing.py
spyrl/agent/__init__.py
spyrl/agent/actor_critic_traces_agent.py
spyrl/agent/agent.py
spyrl/agent/d2dspl_actor_critic_traces_agent.py
spyrl/agent/d2dsql_agent.py
spyrl/agent/d2dsql_agent2.py
spyrl/agent/double_dqn_agent.py
spyrl/agent/double_dqn_agent2.py
spyrl/agent/dqn_agent.py
spyrl/agent/dqn_agent_on_gpu.py
spyrl/agent/dqn_wtn_agent.py
spyrl/agent/mfec_agent.py
spyrl/agent/mo_actor_critic_traces_agent.py
spyrl/agent/mo_dqn_agent.py
spyrl/agent/mo_mnn_dqn_agent.py
spyrl/agent/mo_mnn_dqn_agent_with_mp.py
spyrl/agent/mo_q_learning_traces_agent.py
spyrl/agent/q_learning_agent.py
spyrl/agent/q_learning_traces_agent.py
spyrl/agent/random_agent.py
spyrl/agent/seedable_agent.py
spyrl/agent/torch_seedable_agent.py
spyrl/agent/dqn/__init__.py
spyrl/agent/dqn/dqn.py
spyrl/agent/mfec/__init__.py
spyrl/agent/mfec/mfec_assistant.py
spyrl/agent/mfec/qec.py
spyrl/agent_builder/__init__.py
spyrl/agent_builder/agent_builder.py
spyrl/agent_builder/impl/__init__.py
spyrl/agent_builder/impl/actor_critic_traces_agent_builder.py
spyrl/agent_builder/impl/d2dspl_actor_critic_traces_agent_builder.py
spyrl/agent_builder/impl/mo_actor_critic_traces_agent_builder.py
spyrl/agent_builder/impl/mo_q_learning_traces_agent_builder.py
spyrl/agent_builder/impl/q_learning_agent_builder.py
spyrl/agent_builder/impl/q_learning_traces_agent_builder.py
spyrl/agent_builder/impl/random_agent_builder.py
spyrl/discretiser/__init__.py
spyrl/discretiser/discretiser.py
spyrl/event/__init__.py
spyrl/event/episode_event.py
spyrl/event/session_event.py
spyrl/event/step_event.py
spyrl/event/trial_event.py
spyrl-0.0.1.dist-info/METADATA
spyrl-0.0.1.dist-info/WHEEL
spyrl-0.0.1.dist-info/top_level.txt
spyrl-0.0.1.dist-info/RECORD
