Metadata-Version: 2.1
Name: spyrl
Version: 0.0.1
Summary: A reinforcement learning framework
Home-page: https://github.com/budi-kurniawan/spyrl
Author: Budi Kurniawan
License: UNKNOWN
Platform: UNKNOWN
Classifier: Programming Language :: Python :: 3
Classifier: License :: OSI Approved :: MIT License
Classifier: Operating System :: OS Independent
Requires-Python: >=3.6
